pythumb/__init__.py
pythumb/__main__.py
pythumb/_version.py
pythumb/cli.py
pythumb/core.py
pythumb/exceptions.py
pythumb-1.1.0.dist-info/LICENSE
pythumb-1.1.0.dist-info/METADATA
pythumb-1.1.0.dist-info/NOTICE
pythumb-1.1.0.dist-info/WHEEL
pythumb-1.1.0.dist-info/entry_points.txt
pythumb-1.1.0.dist-info/top_level.txt
pythumb-1.1.0.dist-info/RECORD
